README.txt
setup.cfg
setup.py
TurboKid.egg-info/PKG-INFO
TurboKid.egg-info/SOURCES.txt
TurboKid.egg-info/dependency_links.txt
TurboKid.egg-info/entry_points.txt
TurboKid.egg-info/not-zip-safe
TurboKid.egg-info/requires.txt
TurboKid.egg-info/top_level.txt
turbokid/__init__.py
turbokid/kidsupport.py
turbokid/tests/__init__.py
turbokid/tests/a.kid
turbokid/tests/b.kid
turbokid/tests/c.kid
turbokid/tests/d.kid
turbokid/tests/e.kid
turbokid/tests/extra.kid
turbokid/tests/fruits.kid
turbokid/tests/hello.kid
turbokid/tests/master.kid
turbokid/tests/simple.kid
turbokid/tests/site.kid
turbokid/tests/test_template.py