Metadata-Version: 1.0
Name: TurboKid
Version: 1.0.5
Summary: TurboGears plugin to support use of Kid templates
Home-page: http://docs.turbogears.org/TurboKid
Author: Christoph Zwerschke
Author-email: cito@online.de
License: MIT
Download-URL: http://pypi.python.org/pypi/TurboKid
Keywords: python.templating.engines,turbogears
Platform: UNKNOWN
Classifier: Development Status :: 4 - Beta
Classifier: Framework :: TurboGears
Classifier: Environment :: Web Environment :: Buffet
Classifier: Operating System :: OS Independent
Classifier: Programming Language :: Python
Classifier: License :: OSI Approved :: MIT License
Classifier: Topic :: Software Development :: Libraries :: Python Modules
